catmeow/__init__.py
catmeow/__main__.py
catmeow-0.2.2.dist-info/entry_points.txt
catmeow-0.2.2.dist-info/WHEEL
catmeow-0.2.2.dist-info/METADATA
catmeow-0.2.2.dist-info/RECORD
